techmo/__init__.py
techmo/_version.py
techmo/feature_extraction.py
techmo_wavelet-0.3.2.dist-info/LICENSE.txt
techmo_wavelet-0.3.2.dist-info/METADATA
techmo_wavelet-0.3.2.dist-info/WHEEL
techmo_wavelet-0.3.2.dist-info/top_level.txt
techmo_wavelet-0.3.2.dist-info/RECORD
