Metadata-Version: 2.1
Name: techmo-wavelet
Version: 0.3.2
Summary: A module for audio features extraction from Techmo
Home-page: https://github.com/techmo-pl/vamp-wavelet-fft
Author: Mariusz Ziółko, Michał Kucharski
Author-email: mariusz.ziolko@techmo.pl
License: UNKNOWN
Platform: UNKNOWN
Classifier: Programming Language :: Python :: 3 :: Only
Classifier: Programming Language :: Python :: 3.5
Classifier: Programming Language :: Python :: 3.6
Classifier: Programming Language :: Python :: 3.7
Classifier: Programming Language :: Python :: 3.8
Classifier: Programming Language :: Python :: 3.9
Requires-Python: >=3.5.0
Requires-Dist: scipy
Requires-Dist: PyWavelets (>=1.0.3)
